sharingan/__init__.py
sharingan/__main__.py
sharingan/common.py
sharingan/extract.py
sharingan/log.py
sharingan/models.py
sharingan/sharingan.py
tests/__init__.py
tests/test_common.py
sharingan-0.0.5.dist-info/LICENSE
sharingan-0.0.5.dist-info/METADATA
sharingan-0.0.5.dist-info/WHEEL
sharingan-0.0.5.dist-info/top_level.txt
sharingan-0.0.5.dist-info/RECORD
