Metadata-Version: 2.1
Name: sharingan
Version: 0.0.5
Summary: We will try to find your visible basic footprint from social media as much as possible
Home-page: https://github.com/pypa/sampleproject
Author: s045pd
Author-email: s045pd.x@gmail.com
Classifier: Programming Language :: Python :: 3.8
Classifier: License :: OSI Approved :: MIT License
Classifier: Operating System :: OS Independent
Classifier: Development Status :: 3 - Alpha
Classifier: Framework :: AsyncIO
Requires-Python: >=3.8
License-File: LICENSE
